{
    "img_stem": "dog_443",
    "label": "dog",
    "caption": "The sun casts a warm glow over the lush green field, where a playful black and white dog runs with abandon, its tail wagging furiously as it chases after a ball of fluffy grass. The dog's paws barely touch the ground as it bounds effortlessly across the terrain, its joyful barks carrying on the breeze. In the distance, a few trees sway gently in the wind, their leaves rustling softly against each other as they provide a picturesque backdrop to the lively scene unfolding below.",
    "imgs_paths": {
        "../data/final_dataset_noaug/new_dog/dog_443/new_dog_443.jpg": []
    }
}